otsuwinAPI/__init__.py
otsuwinAPI/kernel32.py
otsuwinAPI/user32.py
otsuwinAPI/constants/__init__.py
otsuwinAPI/constants/hWndInsertAfter.py
otsuwinAPI/constants/nCmdShow.py
otsuwinAPI/constants/uFlags.py
otsuwinAPI-2022.11.30.dist-info/METADATA
otsuwinAPI-2022.11.30.dist-info/WHEEL
otsuwinAPI-2022.11.30.dist-info/top_level.txt
otsuwinAPI-2022.11.30.dist-info/RECORD
