Metadata-Version: 2.1
Name: otsuwinAPI
Version: 2022.11.30
Summary: WindowsAPIを追加していくライブラリ。
Home-page: https://github.com/Otsuhachi/otsuwinAPI
Author: Otsuhachi
Author-email: agequodagis.tufuiegoeris@gmail.com
